pfs2yaml/__init__.py
pfs2yaml/cli.py
pfs2yaml/main.py
pfs2yaml-0.1.0.dist-info/METADATA
pfs2yaml-0.1.0.dist-info/WHEEL
pfs2yaml-0.1.0.dist-info/entry_points.txt
pfs2yaml-0.1.0.dist-info/top_level.txt
pfs2yaml-0.1.0.dist-info/RECORD
