Metadata-Version: 2.1
Name: pfs2yaml
Version: 0.1.0
Summary: A package that can convert DHI pfs files to yaml
Home-page: https://github.com/DHI/pypfs2yaml
Author: Henrik Andersson
Author-email: jan@dhigroup.com
License: MIT
Platform: UNKNOWN
Classifier: License :: OSI Approved :: BSD License
Classifier: Development Status :: 3 - Alpha
Classifier: Intended Audience :: Science/Research
Classifier: Programming Language :: Python
Classifier: Programming Language :: Python :: 3
Classifier: Operating System :: Microsoft :: Windows
Classifier: Topic :: Scientific/Engineering
Requires-Dist: pyyaml
Requires-Dist: click
